LICENSE.txt
README.md
setup.cfg
setup.py
dn_crypto/__init__.py
dn_crypto/crypto.py
dn_crypto/crypto2.py
dn_date_util/__init__.py
dn_date_util/utility.py
dn_financial_pipelines.egg-info/PKG-INFO
dn_financial_pipelines.egg-info/SOURCES.txt
dn_financial_pipelines.egg-info/dependency_links.txt
dn_financial_pipelines.egg-info/requires.txt
dn_financial_pipelines.egg-info/top_level.txt
dn_pricing/__init__.py
dn_pricing/pricing.py
dn_qtrade/__init__.py
dn_qtrade/questrade_2.py